README.md
setup.py
athom/__init__.py
athom/__main__.py
athom/cloud.py
athom/firmware.py
athom/homey.py
athom/token.py
athom/common/__init__.py
athom/common/exceptions.py
athom/common/net.py
athom/common/scopes.py
athom/common/utils.py
athom/common/web.py
athom/managers/__init__.py
athom/managers/apps.py
athom/managers/devices.py
athom/managers/images.py
athom/managers/manager.py
athom/managers/sessions.py
athom/managers/speechInput.py
athom/managers/speechOutput.py
athom/managers/users.py
athom/models/__init__.py
athom/models/avatar.py
athom/models/homey.py
athom/models/role.py
athom/models/update.py
athom/models/user.py
athom/models/userdevice.py
athom/models/managers/__init__.py
athom/models/managers/apps.py
athom/models/managers/capabilities.py
athom/models/managers/devices.py
athom/models/managers/images.py
athom/models/managers/session.py
athom/models/managers/users.py
athom/models/managers/voice.py
athom/storage/__init__.py
athom/storage/localstorage.py
athom_api.egg-info/PKG-INFO
athom_api.egg-info/SOURCES.txt
athom_api.egg-info/dependency_links.txt
athom_api.egg-info/entry_points.txt
athom_api.egg-info/requires.txt
athom_api.egg-info/top_level.txt