Metadata-Version: 2.1
Name: athom-api
Version: 1.1.0
Summary: A python module for accessing the Athom Web-API for use with the Athom Homey
Home-page: https://github.com/rkokkelk/python-athom-api
Author: Roy K
Author-email: rkokk@protonmail.com
License: GPLv3
Keywords: API athom homey
Platform: UNKNOWN
Classifier: Development Status :: 3 - Alpha
Classifier: Intended Audience :: Developers
Classifier: Programming Language :: Python :: 3
Classifier: Programming Language :: Python :: 3.6
Classifier: Programming Language :: Python :: 3.7
Classifier: Topic :: Home Automation
